[{
  "_id": {
    "$oid": "66c0afaf871ca9641884194b"
  },
  "userId": {
    "$oid": "66bcce22dd268e7fb5c1d2aa"
  },
  "templateId": {
    "$oid": "66c0af42871ca96418841905"
  },
  "pageId": {
    "$oid": "66c0af42871ca96418841908"
  },
  "url": "http://localhost:3000/sdfrg/home",
  "visitCount": 1,
  "createdAt": {
    "$date": "2024-08-17T14:11:59.618Z"
  },
  "updatedAt": {
    "$date": "2024-08-17T14:11:59.618Z"
  },
  "__v": 0
},
{
  "_id": {
    "$oid": "66c49bc2dbaaa232bb140fef"
  },
  "userId": {
    "$oid": "66bcce22dd268e7fb5c1d2aa"
  },
  "templateId": {
    "$oid": "66c41c27d1e02e31c1091348"
  },
  "pageId": {
    "$oid": "66c41c27d1e02e31c109134b"
  },
  "url": "das@sda.COM",
  "visitCount": 1,
  "createdAt": {
    "$date": "2024-08-20T13:36:02.394Z"
  },
  "updatedAt": {
    "$date": "2024-08-20T13:36:02.394Z"
  },
  "__v": 0
}]