[{
  "_id": {
    "$oid": "66be4768ce0bca957fdfc117"
  },
  "userId": {
    "$oid": "66bcce22dd268e7fb5c1d2aa"
  },
  "templateId": {
    "$oid": "66be4749ce0bca957fdfc0f1"
  },
  "visitCount": 2,
  "ipAddress": "::1",
  "createdAt": {
    "$date": "2024-08-15T18:22:32.664Z"
  },
  "updatedAt": {
    "$date": "2024-08-16T11:20:33.753Z"
  },
  "__v": 0
},
{
  "_id": {
    "$oid": "66bf2da87e37317a852c57e1"
  },
  "userId": {
    "$oid": "66bcce22dd268e7fb5c1d2aa"
  },
  "templateId": {
    "$oid": "66be5755ce0bca957fdfc24f"
  },
  "visitCount": 1,
  "ipAddress": "::1",
  "createdAt": {
    "$date": "2024-08-16T10:44:56.605Z"
  },
  "updatedAt": {
    "$date": "2024-08-16T10:44:56.605Z"
  },
  "__v": 0
},
{
  "_id": {
    "$oid": "66bf37657e37317a852c58cf"
  },
  "userId": {
    "$oid": "66bcce22dd268e7fb5c1d2aa"
  },
  "templateId": {
    "$oid": "66bf37297e37317a852c5883"
  },
  "visitCount": 1,
  "ipAddress": "::1",
  "createdAt": {
    "$date": "2024-08-16T11:26:29.883Z"
  },
  "updatedAt": {
    "$date": "2024-08-16T11:26:29.883Z"
  },
  "__v": 0
},
{
  "_id": {
    "$oid": "66bf39677e37317a852c595b"
  },
  "userId": {
    "$oid": "66bcce22dd268e7fb5c1d2aa"
  },
  "templateId": {
    "$oid": "66bf39487e37317a852c5926"
  },
  "visitCount": 1,
  "ipAddress": "::1",
  "createdAt": {
    "$date": "2024-08-16T11:35:03.270Z"
  },
  "updatedAt": {
    "$date": "2024-08-16T11:35:03.270Z"
  },
  "__v": 0
},
{
  "_id": {
    "$oid": "66c0afb0871ca96418841958"
  },
  "userId": {
    "$oid": "66bcce22dd268e7fb5c1d2aa"
  },
  "templateId": {
    "$oid": "66c0af42871ca96418841905"
  },
  "visitCount": 1,
  "ipAddress": "::1",
  "createdAt": {
    "$date": "2024-08-17T14:12:00.705Z"
  },
  "updatedAt": {
    "$date": "2024-08-17T14:12:00.705Z"
  },
  "__v": 0
},
{
  "_id": {
    "$oid": "66c0bd42871ca96418841c03"
  },
  "userId": {
    "$oid": "66bcce22dd268e7fb5c1d2aa"
  },
  "templateId": {
    "$oid": "66c0bd29871ca96418841bb9"
  },
  "visitCount": 1,
  "ipAddress": "::1",
  "createdAt": {
    "$date": "2024-08-17T15:09:54.218Z"
  },
  "updatedAt": {
    "$date": "2024-08-17T15:09:54.218Z"
  },
  "__v": 0
},
{
  "_id": {
    "$oid": "66c0e4e9568ada02c7a28802"
  },
  "userId": {
    "$oid": "66bcce22dd268e7fb5c1d2aa"
  },
  "templateId": {
    "$oid": "66c0cf32568ada02c7a28685"
  },
  "visitCount": 1,
  "ipAddress": "::1",
  "createdAt": {
    "$date": "2024-08-17T17:59:05.284Z"
  },
  "updatedAt": {
    "$date": "2024-08-17T17:59:05.284Z"
  },
  "__v": 0
},
{
  "_id": {
    "$oid": "66c219d859a916453aee2a08"
  },
  "userId": {
    "$oid": "66bcce22dd268e7fb5c1d2aa"
  },
  "templateId": {
    "$oid": "66c219af59a916453aee29b3"
  },
  "visitCount": 1,
  "ipAddress": "::1",
  "createdAt": {
    "$date": "2024-08-18T15:57:12.662Z"
  },
  "updatedAt": {
    "$date": "2024-08-18T15:57:12.662Z"
  },
  "__v": 0
},
{
  "_id": {
    "$oid": "66c21a4959a916453aee2a8d"
  },
  "userId": {
    "$oid": "66bcce22dd268e7fb5c1d2aa"
  },
  "templateId": {
    "$oid": "66c21a2359a916453aee2a3a"
  },
  "visitCount": 1,
  "ipAddress": "::1",
  "createdAt": {
    "$date": "2024-08-18T15:59:05.400Z"
  },
  "updatedAt": {
    "$date": "2024-08-18T15:59:05.400Z"
  },
  "__v": 0
},
{
  "_id": {
    "$oid": "66c21b2059a916453aee2c2a"
  },
  "userId": {
    "$oid": "66bcce22dd268e7fb5c1d2aa"
  },
  "templateId": {
    "$oid": "66c21b0259a916453aee2bc0"
  },
  "visitCount": 1,
  "ipAddress": "::1",
  "createdAt": {
    "$date": "2024-08-18T16:02:40.493Z"
  },
  "updatedAt": {
    "$date": "2024-08-18T16:02:40.493Z"
  },
  "__v": 0
},
{
  "_id": {
    "$oid": "66c21c2159a916453aee2cd8"
  },
  "userId": {
    "$oid": "66bcce22dd268e7fb5c1d2aa"
  },
  "templateId": {
    "$oid": "66c21b3359a916453aee2c4a"
  },
  "visitCount": 1,
  "ipAddress": "::1",
  "createdAt": {
    "$date": "2024-08-18T16:06:57.429Z"
  },
  "updatedAt": {
    "$date": "2024-08-18T16:06:57.429Z"
  },
  "__v": 0
},
{
  "_id": {
    "$oid": "66c21f3b59a916453aee2ed2"
  },
  "userId": {
    "$oid": "66bcce22dd268e7fb5c1d2aa"
  },
  "templateId": {
    "$oid": "66c21e5a59a916453aee2e00"
  },
  "visitCount": 1,
  "ipAddress": "::1",
  "createdAt": {
    "$date": "2024-08-18T16:20:11.305Z"
  },
  "updatedAt": {
    "$date": "2024-08-18T16:20:11.305Z"
  },
  "__v": 0
},
{
  "_id": {
    "$oid": "66c21f3e59a916453aee2ee3"
  },
  "userId": {
    "$oid": "66bcce22dd268e7fb5c1d2aa"
  },
  "templateId": {
    "$oid": "66c21ef859a916453aee2e77"
  },
  "visitCount": 1,
  "ipAddress": "::1",
  "createdAt": {
    "$date": "2024-08-18T16:20:14.942Z"
  },
  "updatedAt": {
    "$date": "2024-08-18T16:20:14.942Z"
  },
  "__v": 0
},
{
  "_id": {
    "$oid": "66c2211d59a916453aee2fa5"
  },
  "userId": {
    "$oid": "66bcce22dd268e7fb5c1d2aa"
  },
  "templateId": {
    "$oid": "66c2210959a916453aee2f5d"
  },
  "visitCount": 1,
  "ipAddress": "::1",
  "createdAt": {
    "$date": "2024-08-18T16:28:13.905Z"
  },
  "updatedAt": {
    "$date": "2024-08-18T16:28:13.905Z"
  },
  "__v": 0
},
{
  "_id": {
    "$oid": "66c2217359a916453aee300e"
  },
  "userId": {
    "$oid": "66bcce22dd268e7fb5c1d2aa"
  },
  "templateId": {
    "$oid": "66c2215859a916453aee2fc1"
  },
  "visitCount": 1,
  "ipAddress": "::1",
  "createdAt": {
    "$date": "2024-08-18T16:29:39.433Z"
  },
  "updatedAt": {
    "$date": "2024-08-18T16:29:39.433Z"
  },
  "__v": 0
},
{
  "_id": {
    "$oid": "66c221a959a916453aee3094"
  },
  "userId": {
    "$oid": "66bcce22dd268e7fb5c1d2aa"
  },
  "templateId": {
    "$oid": "66c2219759a916453aee304a"
  },
  "visitCount": 1,
  "ipAddress": "::1",
  "createdAt": {
    "$date": "2024-08-18T16:30:33.889Z"
  },
  "updatedAt": {
    "$date": "2024-08-18T16:30:33.889Z"
  },
  "__v": 0
},
{
  "_id": {
    "$oid": "66c2239159a916453aee31cb"
  },
  "userId": {
    "$oid": "66bcce22dd268e7fb5c1d2aa"
  },
  "templateId": {
    "$oid": "66c2231359a916453aee3165"
  },
  "visitCount": 1,
  "ipAddress": "::1",
  "createdAt": {
    "$date": "2024-08-18T16:38:41.223Z"
  },
  "updatedAt": {
    "$date": "2024-08-18T16:38:41.223Z"
  },
  "__v": 0
},
{
  "_id": {
    "$oid": "66c223c559a916453aee3224"
  },
  "userId": {
    "$oid": "66bcce22dd268e7fb5c1d2aa"
  },
  "templateId": {
    "$oid": "66c223a059a916453aee31da"
  },
  "visitCount": 1,
  "ipAddress": "::1",
  "createdAt": {
    "$date": "2024-08-18T16:39:33.208Z"
  },
  "updatedAt": {
    "$date": "2024-08-18T16:39:33.208Z"
  },
  "__v": 0
},
{
  "_id": {
    "$oid": "66c224f359a916453aee32b3"
  },
  "userId": {
    "$oid": "66bcce22dd268e7fb5c1d2aa"
  },
  "templateId": {
    "$oid": "66c224d259a916453aee3263"
  },
  "visitCount": 1,
  "ipAddress": "::1",
  "createdAt": {
    "$date": "2024-08-18T16:44:35.831Z"
  },
  "updatedAt": {
    "$date": "2024-08-18T16:44:35.831Z"
  },
  "__v": 0
},
{
  "_id": {
    "$oid": "66c22a7f59a916453aee3311"
  },
  "userId": {
    "$oid": "66bcce22dd268e7fb5c1d2aa"
  },
  "templateId": {
    "$oid": "66c2250659a916453aee32cb"
  },
  "visitCount": 1,
  "ipAddress": "::1",
  "createdAt": {
    "$date": "2024-08-18T17:08:15.372Z"
  },
  "updatedAt": {
    "$date": "2024-08-18T17:08:15.372Z"
  },
  "__v": 0
},
{
  "_id": {
    "$oid": "66c2d9f182fb5cafd5ca330c"
  },
  "userId": {
    "$oid": "66bcce22dd268e7fb5c1d2aa"
  },
  "templateId": {
    "$oid": "66c2d7b782fb5cafd5ca31a1"
  },
  "visitCount": 3,
  "ipAddress": "::1",
  "createdAt": {
    "$date": "2024-08-19T05:36:49.403Z"
  },
  "updatedAt": {
    "$date": "2024-08-19T15:17:45.192Z"
  },
  "__v": 0
},
{
  "_id": {
    "$oid": "66c36264a56ebee2ddfab2d4"
  },
  "userId": {
    "$oid": "66bcce22dd268e7fb5c1d2aa"
  },
  "templateId": {
    "$oid": "66c36244a56ebee2ddfab286"
  },
  "visitCount": 1,
  "ipAddress": "::1",
  "createdAt": {
    "$date": "2024-08-19T15:19:00.642Z"
  },
  "updatedAt": {
    "$date": "2024-08-19T15:19:00.642Z"
  },
  "__v": 0
},
{
  "_id": {
    "$oid": "66c37a47a56ebee2ddfab5d1"
  },
  "userId": {
    "$oid": "66bcce22dd268e7fb5c1d2aa"
  },
  "templateId": {
    "$oid": "66c37a2fa56ebee2ddfab582"
  },
  "visitCount": 1,
  "ipAddress": "::1",
  "createdAt": {
    "$date": "2024-08-19T17:00:55.949Z"
  },
  "updatedAt": {
    "$date": "2024-08-19T17:00:55.949Z"
  },
  "__v": 0
},
{
  "_id": {
    "$oid": "66c3851ec8b4ff9f9b9da656"
  },
  "userId": {
    "$oid": "66bcce22dd268e7fb5c1d2aa"
  },
  "templateId": {
    "$oid": "66c384e4c8b4ff9f9b9da609"
  },
  "visitCount": 1,
  "ipAddress": "::1",
  "createdAt": {
    "$date": "2024-08-19T17:47:10.682Z"
  },
  "updatedAt": {
    "$date": "2024-08-19T17:47:10.682Z"
  },
  "__v": 0
},
{
  "_id": {
    "$oid": "66c41805d1e02e31c1091229"
  },
  "userId": {
    "$oid": "66bcce22dd268e7fb5c1d2aa"
  },
  "templateId": {
    "$oid": "66c390a91481f20fa4b8461f"
  },
  "visitCount": 1,
  "ipAddress": "::1",
  "createdAt": {
    "$date": "2024-08-20T04:13:57.950Z"
  },
  "updatedAt": {
    "$date": "2024-08-20T04:13:57.950Z"
  },
  "__v": 0
},
{
  "_id": {
    "$oid": "66c41bcbd1e02e31c1091333"
  },
  "userId": {
    "$oid": "66bcce22dd268e7fb5c1d2aa"
  },
  "templateId": {
    "$oid": "66c4188ad1e02e31c109129c"
  },
  "visitCount": 1,
  "ipAddress": "::1",
  "createdAt": {
    "$date": "2024-08-20T04:30:03.723Z"
  },
  "updatedAt": {
    "$date": "2024-08-20T04:30:03.723Z"
  },
  "__v": 0
},
{
  "_id": {
    "$oid": "66c41c81d1e02e31c10913a7"
  },
  "userId": {
    "$oid": "66bcce22dd268e7fb5c1d2aa"
  },
  "templateId": {
    "$oid": "66c41c27d1e02e31c1091348"
  },
  "visitCount": 2,
  "ipAddress": "::1",
  "createdAt": {
    "$date": "2024-08-20T04:33:05.197Z"
  },
  "updatedAt": {
    "$date": "2024-08-20T13:25:35.789Z"
  },
  "__v": 0
},
{
  "_id": {
    "$oid": "66c49f7de2eed6dbeea2e2ab"
  },
  "userId": {
    "$oid": "66bcce22dd268e7fb5c1d2aa"
  },
  "templateId": {
    "$oid": "66c49f64e2eed6dbeea2e24e"
  },
  "visitCount": 2,
  "ipAddress": "127.0.0.1",
  "createdAt": {
    "$date": "2024-08-20T13:51:57.471Z"
  },
  "updatedAt": {
    "$date": "2024-08-20T16:31:47.113Z"
  },
  "__v": 0
},
{
  "_id": {
    "$oid": "66c4d3f545b1f8f1cef1d24d"
  },
  "userId": {
    "$oid": "66bcce22dd268e7fb5c1d2aa"
  },
  "templateId": {
    "$oid": "66c4d33945b1f8f1cef1d19a"
  },
  "visitCount": 1,
  "ipAddress": "::1",
  "createdAt": {
    "$date": "2024-08-20T17:35:49.259Z"
  },
  "updatedAt": {
    "$date": "2024-08-20T17:35:49.259Z"
  },
  "__v": 0
},
{
  "_id": {
    "$oid": "66c4dc6545b1f8f1cef1d4a4"
  },
  "userId": {
    "$oid": "66bcce22dd268e7fb5c1d2aa"
  },
  "templateId": {
    "$oid": "66c4db1345b1f8f1cef1d448"
  },
  "visitCount": 2,
  "ipAddress": "::1",
  "createdAt": {
    "$date": "2024-08-20T18:11:49.322Z"
  },
  "updatedAt": {
    "$date": "2024-08-21T14:12:20.604Z"
  },
  "__v": 0
},
{
  "_id": {
    "$oid": "66c4dfd645b1f8f1cef1d543"
  },
  "userId": {
    "$oid": "66bcce22dd268e7fb5c1d2aa"
  },
  "templateId": {
    "$oid": "66c4dfb945b1f8f1cef1d4ff"
  },
  "visitCount": 2,
  "ipAddress": "::1",
  "createdAt": {
    "$date": "2024-08-20T18:26:30.090Z"
  },
  "updatedAt": {
    "$date": "2024-08-21T14:07:32.087Z"
  },
  "__v": 0
},
{
  "_id": {
    "$oid": "66c5f5be898cc1ce9eec4ce7"
  },
  "userId": {
    "$oid": "66bcce22dd268e7fb5c1d2aa"
  },
  "templateId": {
    "$oid": "66c4d33945b1f8f1cef1d19a"
  },
  "visitCount": 1,
  "ipAddress": "::1",
  "createdAt": {
    "$date": "2024-08-21T14:12:14.444Z"
  },
  "updatedAt": {
    "$date": "2024-08-21T14:12:14.444Z"
  },
  "__v": 0
},
{
  "_id": {
    "$oid": "66c6b02c83a1f1c5ae57757c"
  },
  "userId": {
    "$oid": "66bcce22dd268e7fb5c1d2aa"
  },
  "templateId": {
    "$oid": "66c4dfb945b1f8f1cef1d4ff"
  },
  "visitCount": 1,
  "ipAddress": "::1",
  "createdAt": {
    "$date": "2024-08-22T03:27:40.024Z"
  },
  "updatedAt": {
    "$date": "2024-08-22T03:27:40.024Z"
  },
  "__v": 0
},
{
  "_id": {
    "$oid": "66c6b05d83a1f1c5ae5775fa"
  },
  "userId": {
    "$oid": "66bcce22dd268e7fb5c1d2aa"
  },
  "templateId": {
    "$oid": "66c6b04d83a1f1c5ae5775b9"
  },
  "visitCount": 1,
  "ipAddress": "::1",
  "createdAt": {
    "$date": "2024-08-22T03:28:29.810Z"
  },
  "updatedAt": {
    "$date": "2024-08-22T03:28:29.810Z"
  },
  "__v": 0
},
{
  "_id": {
    "$oid": "66c6b32683a1f1c5ae57767f"
  },
  "userId": {
    "$oid": "66bcce22dd268e7fb5c1d2aa"
  },
  "templateId": {
    "$oid": "66c6b30f83a1f1c5ae577637"
  },
  "visitCount": 1,
  "ipAddress": "::1",
  "createdAt": {
    "$date": "2024-08-22T03:40:22.950Z"
  },
  "updatedAt": {
    "$date": "2024-08-22T03:40:22.950Z"
  },
  "__v": 0
},
{
  "_id": {
    "$oid": "66c77369d9798e9d90597e40"
  },
  "userId": {
    "$oid": "66bcce22dd268e7fb5c1d2aa"
  },
  "templateId": {
    "$oid": "66c7731ed9798e9d90597dff"
  },
  "visitCount": 1,
  "ipAddress": "::1",
  "createdAt": {
    "$date": "2024-08-22T17:20:41.926Z"
  },
  "updatedAt": {
    "$date": "2024-08-22T17:20:41.926Z"
  },
  "__v": 0
},
{
  "_id": {
    "$oid": "66ca0c2f946cd3ea2a0758a6"
  },
  "userId": {
    "$oid": "66bcce22dd268e7fb5c1d2aa"
  },
  "templateId": {
    "$oid": "66c7731ed9798e9d90597dff"
  },
  "visitCount": 1,
  "ipAddress": "::1",
  "createdAt": {
    "$date": "2024-08-24T16:37:03.909Z"
  },
  "updatedAt": {
    "$date": "2024-08-24T16:37:03.909Z"
  },
  "__v": 0
},
{
  "_id": {
    "$oid": "66cb4079d08e4b2da8ab0de2"
  },
  "userId": {
    "$oid": "66bcce22dd268e7fb5c1d2aa"
  },
  "templateId": {
    "$oid": "66c7731ed9798e9d90597dff"
  },
  "visitCount": 1,
  "ipAddress": "::1",
  "createdAt": {
    "$date": "2024-08-25T14:32:26.007Z"
  },
  "updatedAt": {
    "$date": "2024-08-25T14:32:26.007Z"
  },
  "__v": 0
}]